CanvasSync/__init__.py
CanvasSync/_version.py
CanvasSync/usage.py
CanvasSync/entities/__init__.py
CanvasSync/entities/assignment.py
CanvasSync/entities/assignments_folder.py
CanvasSync/entities/canvas_entity.py
CanvasSync/entities/course.py
CanvasSync/entities/external_url.py
CanvasSync/entities/file.py
CanvasSync/entities/folder.py
CanvasSync/entities/linked_file.py
CanvasSync/entities/module.py
CanvasSync/entities/page.py
CanvasSync/entities/sub_header.py
CanvasSync/entities/synchronizer.py
CanvasSync/settings/__init__.py
CanvasSync/settings/cryptography.py
CanvasSync/settings/settings.py
CanvasSync/settings/user_prompter.py
CanvasSync/utilities/ANSI.py
CanvasSync/utilities/__init__.py
CanvasSync/utilities/helpers.py
CanvasSync/utilities/instructure_api.py
CanvasSync/utilities/url_shortcut_maker.py
bin/__init__.py
bin/canvas.py
sidp_CanvasSync-0.2.4.dist-info/LICENSE.txt
sidp_CanvasSync-0.2.4.dist-info/METADATA
sidp_CanvasSync-0.2.4.dist-info/WHEEL
sidp_CanvasSync-0.2.4.dist-info/entry_points.txt
sidp_CanvasSync-0.2.4.dist-info/top_level.txt
sidp_CanvasSync-0.2.4.dist-info/RECORD
