Metadata-Version: 2.1
Name: sidp-CanvasSync
Version: 0.2.4
Summary: Synchronizes modules, assignments and files from a Canvas server to a local folder
Home-page: https://github.com/sidpagariya/CanvasSync
Author: Sid Pagariya, Mathias Perslev
Author-email: sid@sidp.me
License: LICENSE.txt
Platform: UNKNOWN
Classifier: Development Status :: 3 - Alpha
Classifier: Environment :: Console
Classifier: Operating System :: MacOS :: MacOS X
Classifier: Operating System :: POSIX
Classifier: Programming Language :: Python
Classifier: License :: OSI Approved :: MIT License
Requires-Dist: requests
Requires-Dist: pycryptodome
Requires-Dist: py-bcrypt
Requires-Dist: six
